[
  {
    "model": "workflows.abstractwidget", 
    "fields": {
      "category": "57cfe571-165d-4575-90d9-28daf794e773", 
      "treeview_image": "", 
      "name": "Add Labels", 
      "is_streaming": false, 
      "uid": "37acf878-eea5-4d81-9b60-bcfd6dd7ed51", 
      "interaction_view": "", 
      "image": "", 
      "package": "tf_core.nltoolkit", 
      "static_image": "dataset_add_labels_image.png", 
      "windows_queue": false, 
      "post_interact_action": "", 
      "visualization_view": "", 
      "streaming_visualization_view": "", 
      "action": "add_labels_to_document_vectors", 
      "wsdl_method": "", 
      "wsdl": "", 
      "interactive": false, 
      "has_progress_bar": false, 
      "order": 1, 
      "description": "Automatically generated widget from function AddLabelsToDocumentVectors in package latino. The original function signature: AddLabelsToDocumentVectors."
    }
  }, 
  {
    "model": "workflows.abstractinput", 
    "fields": {
      "widget": "37acf878-eea5-4d81-9b60-bcfd6dd7ed51", 
      "name": "Dataset", 
      "short_name": "ds", 
      "uid": "9f466a6e-1a73-4cd5-8ae5-1bf634daaefc", 
      "default": "", 
      "required": true, 
      "multi": false, 
      "parameter_type": null, 
      "variable": "ds", 
      "parameter": false, 
      "order": 1, 
      "description": "Latino.Model.LabeledDataset`2[[System.String, mscorlib, Version=4.0.0.0, Culture=neutral, PublicKeyToken=b77a5c561934e089],[Latino.SparseVector`1[[System.Double, mscorlib, Version=4.0.0.0, Culture=neutral, PublicKeyToken=b77a5c561934e089]], Latino, Version=1.0.0.0, Culture=neutral, PublicKeyToken=null]]"
    }
  }, 
  {
    "model": "workflows.abstractinput", 
    "fields": {
      "widget": "37acf878-eea5-4d81-9b60-bcfd6dd7ed51", 
      "name": "Labeles (Array of Strings)", 
      "short_name": "str", 
      "uid": "eb8485af-ea8c-4feb-ae41-dbb76a52a807", 
      "default": "", 
      "required": true, 
      "multi": false, 
      "parameter_type": "textarea", 
      "variable": "labels", 
      "parameter": false, 
      "order": 2, 
      "description": "System.Collections.Generic.List`1[[System.String, mscorlib, Version=4.0.0.0, Culture=neutral, PublicKeyToken=b77a5c561934e089]]"
    }
  }, 
  {
    "model": "workflows.abstractoutput", 
    "fields": {
      "widget": "37acf878-eea5-4d81-9b60-bcfd6dd7ed51", 
      "name": "Dataset", 
      "short_name": "ds", 
      "variable": "ds", 
      "uid": "a5f5d324-1f48-4223-911a-889736b53a90", 
      "order": 1, 
      "description": ""
    }
  }
]