[
  {
    "model": "workflows.abstractwidget", 
    "fields": {
      "uid": "5746f13a-5cb8-4472-adcd-9e7deb7b540c", 
      "has_file": false, 
      "image": "", 
      "description": "This is the Porter stemming algorithm, ported to Python from the version coded up in ANSI C by the author. It follows the algorithm presented in \r\n\r\nPorter, M. \"An algorithm for suffix stripping.\" Program 14.3 (1980): 130-137.\r\n\r\nonly differing from it at the points marked --DEPARTURE-- and --NEW--\r\nbelow.\r\n\r\nFor a more faithful version of the Porter algorithm, see\r\nhttp://www.tartarus.org/~martin/PorterStemmer/\r\n", 
      "category": "017444c3-afd0-4300-9766-bedeaef10765", 
      "interaction_view": "", 
      "streaming_visualization_view": "", 
      "treeview_image": "", 
      "is_streaming": false, 
      "windows_queue": false, 
      "static_image": "tag_stem_image.png", 
      "action": "nltk_porter_stemmer", 
      "wsdl": "", 
      "name": "Porter Stemmer", 
      "package": "tf_core.nltoolkit", 
      "visualization_view": "", 
      "post_interact_action": "", 
      "wsdl_method": "", 
      "has_progress_bar": false, 
      "order": 7, 
      "interactive": false
    }
  }, 
  {
    "model": "workflows.abstractoutput", 
    "fields": {
      "widget": "5746f13a-5cb8-4472-adcd-9e7deb7b540c", 
      "name": "Stemmer (Tagger)", 
      "short_name": "tgr", 
      "variable": "tagger", 
      "uid": "30a0c173-06ee-4726-a1d7-110f0ec84ed4", 
      "order": 1, 
      "description": ""
    }
  }
]